pyprobeplus/__init__.py
pyprobeplus/const.py
pyprobeplus/exceptions.py
pyprobeplus/parser.py
pyprobeplus-1.1.2.dist-info/licenses/LICENSE
pyprobeplus-1.1.2.dist-info/METADATA
pyprobeplus-1.1.2.dist-info/WHEEL
pyprobeplus-1.1.2.dist-info/entry_points.txt
pyprobeplus-1.1.2.dist-info/top_level.txt
pyprobeplus-1.1.2.dist-info/RECORD
